funwavetvdtools/__init__.py
funwavetvdtools/error.py
funwavetvdtools/grid/__init__.py
funwavetvdtools/grid/common.py
funwavetvdtools/grid/filter.py
funwavetvdtools/grid/interpolation.py
funwavetvdtools/grid/scatter.py
funwavetvdtools/grid/structured.py
funwavetvdtools/grid/subgrids.py
funwavetvdtools/grid/variable.py
funwavetvdtools/io/__init__.py
funwavetvdtools/io/field.py
funwavetvdtools/io/generateinputparameters_build.py
funwavetvdtools/io/input_parameters.csv
funwavetvdtools/io/parameter.py
funwavetvdtools/math/__init__.py
funwavetvdtools/math/geometry.py
funwavetvdtools/math/interpolation.py
funwavetvdtools/math/newtonraphson.py
funwavetvdtools/misc/__init__.py
funwavetvdtools/misc/justifylines.py
funwavetvdtools/parallel/simple.py
funwavetvdtools/plotting/__init__.py
funwavetvdtools/plotting/colorbars.py
funwavetvdtools/plotting/tools/__init__.py
funwavetvdtools/plotting/tools/advance_box_edit_tool.py
funwavetvdtools/plotting/tools/advance_box_edit_tool_buttons.js
funwavetvdtools/plotting/tools/advance_box_edit_tool_select.js
funwavetvdtools/plotting/tools/customjs.py
funwavetvdtools/plotting/tools/svg_icons.py
funwavetvdtools/stations/__init__.py
funwavetvdtools/stations/overtopping.py
funwavetvdtools/stations/reflection.py
funwavetvdtools/stations/runup.py
funwavetvdtools/stations/stations.py
funwavetvdtools/structures/__init__.py
funwavetvdtools/structures/eurotop_2018.py
funwavetvdtools/validation.py
funwavetvdtools/waves/__init__.py
funwavetvdtools/waves/dispersion.py
funwavetvdtools-0.1.1.dist-info/LICENSE
funwavetvdtools-0.1.1.dist-info/METADATA
funwavetvdtools-0.1.1.dist-info/WHEEL
funwavetvdtools-0.1.1.dist-info/RECORD
